msql_driver-0.8.0.dist-info/METADATA
msql_driver-0.8.0.dist-info/WHEEL
msql_driver-0.8.0.dist-info/licenses/LICENSE.txt
msql_driver/__init__.py
msql_driver/__init__.pyi
msql_driver/_msql_driver_py.abi3.so
msql_driver-0.8.0.dist-info/RECORD
