Metadata-Version: 2.4
Name: msql-driver
Version: 0.8.0
Classifier: Development Status :: 4 - Beta
Classifier: Environment :: Console
Classifier: Intended Audience :: Developers
Classifier: Intended Audience :: Science/Research
Classifier: License :: OSI Approved :: BSD License
Classifier: Operating System :: MacOS
Classifier: Operating System :: Microsoft :: Windows
Classifier: Operating System :: POSIX :: Linux
Classifier: Programming Language :: Python
Classifier: Programming Language :: Python :: 3
Classifier: Programming Language :: Python :: 3 :: Only
Classifier: Programming Language :: Python :: 3.10
Classifier: Programming Language :: Python :: 3.11
Classifier: Programming Language :: Python :: 3.12
Classifier: Programming Language :: Python :: 3.13
Classifier: Programming Language :: Python :: 3.14
Classifier: Programming Language :: Python :: Implementation :: CPython
Classifier: Programming Language :: Rust
Classifier: Topic :: Database
Classifier: Topic :: Database :: Front-Ends
Classifier: Topic :: Scientific/Engineering
Classifier: Topic :: Scientific/Engineering :: GIS
Classifier: Topic :: Scientific/Engineering :: Information Analysis
Classifier: Topic :: Software Development
Classifier: Typing :: Typed
Requires-Dist: numpy~=2.2 ; extra == 'numpy'
Requires-Dist: pandas~=2.3 ; extra == 'pandas'
Requires-Dist: msql-driver[numpy,pandas] ; extra == 'all'
Provides-Extra: numpy
Provides-Extra: pandas
Provides-Extra: all
License-File: LICENSE.txt
Summary: Mireo SpaceTime MSQL connector
Keywords: mireo,spacetime,msql,connector,sql,query,spatiotemporal,database
Author: Mireo
Maintainer-email: Zvonimir Jurelinac <zvonimir.jurelinac@mireo.com>
Requires-Python: >=3.10
Project-URL: Homepage, https://www.mireo.com/spacetime
Project-URL: MSQL Reference, https://spacetime.mireo.com/msql/
Project-URL: SpaceTime Live Demo, https://spacetime.mireo.com/
